Workbook
Name aporte: Finance_simulator!$D$14:$D$14
Name patrimonio: Finance_simulator!$D$17:$D$17
Name qtd_anos: Finance_simulator!$D$15:$D$15
Name rendimento_carteira: Finance_simulator!$D$10:$D$10
Name salario: Finance_simulator!$D$9:$D$9
Name sugestao_investimento: Finance_simulator!$D$11:$D$11
Name taxa_mensal: Finance_simulator!$D$16:$D$16
Name taxa_mensall: Finance_simulator!$D$16:$D$16

Sheet Finance_simulator
B8: INFORMAÇÕES BÁSICAS
B9: Salário atual | D9: 2000
B10: Rendimento Carteira | D10: 0.006
B11: Sugestão de investimento (30%) | D11: {=salario*30%} -> 600
B13: DEFINIÇÃO DE APORTE
B14: Quanto investir por mês? | D14: 200
B15: Quantos anos devo investir? | D15: 5
B16: taxa de rendimento mensal? | D16: 0.01079
B17: Quanto de patrimônio total acumulado? | D17: {=FV(taxa_mensal,qtd_anos*12,aporte*-1)} -> 16755.383
B18: Quanto de dividendo mensais? | D18: {=patrimonio*rendimento_carteira} -> 100.5323
B20: CENÁRIOS FUTUROS | D20: Dividendos
A21: 2 | B21: Quanto em 2 anos ? | C21: =FV($D$16,$A21*12,$D$14*-1) -> 5445.5255 | D21: {=C21*rendimento_carteira} -> 32.673153
A22: 5 | B22: Quanto em 5 anos ? | C22: =FV($D$16,$A22*12,$D$14*-1) -> 16755.383 | D22: {=C22*rendimento_carteira} -> 100.5323
A23: 10 | B23: Quanto em 10 anos ? | C23: =FV($D$16,$A23*12,$D$14*-1) -> 48656.843 | D23: {=C23*rendimento_carteira} -> 291.94106
A24: 20 | B24: Quanto em 20 anos ? | C24: =FV($D$16,$A24*12,$D$14*-1) -> 225039.68 | D24: {=C24*rendimento_carteira} -> 1350.2381
A25: 30 | B25: Quanto em 30 anos ? | C25: =FV($D$16,$A25*12,$D$14*-1) -> 864433.93 | D25: {=C25*rendimento_carteira} -> 5186.6036
B27: PERFIL | C27: Moderado
B28: VALOR A SER INVESTIDO POR MÊS | C28: =D14 -> 200
B30: TIPO DE FII | C30: Percentual sugerido | D30: Valores
B31: PAPEL | C31: =VLOOKUP($C$27&"-"&B31,Base_perfil!$A:$D,4,FALSE) -> 0.32 | D31: =C31*$C$28 -> 64
B32: TIJOLO | C32: =VLOOKUP($C$27&"-"&B32,Base_perfil!$A:$D,4,FALSE) -> 0.35 | D32: =C32*$C$28 -> 70
B33: HÍBRIDOS | C33: =VLOOKUP($C$27&"-"&B33,Base_perfil!$A:$D,4,FALSE) -> 0.08 | D33: =C33*$C$28 -> 16
B34: FOFs | C34: =VLOOKUP($C$27&"-"&B34,Base_perfil!$A:$D,4,FALSE) -> 0.05 | D34: =C34*$C$28 -> 10
B35: DESENVOLVIMENTO | C35: =VLOOKUP($C$27&"-"&B35,Base_perfil!$A:$D,4,FALSE) -> 0.1 | D35: =C35*$C$28 -> 20
B36: HOTELARIAS | C36: =VLOOKUP($C$27&"-"&B36,Base_perfil!$A:$D,4,FALSE) -> 0.1 | D36: =C36*$C$28 -> 20
B37: TOTAL | D37: =SUM(D31:D36) -> 200

Sheet Base_perfil
A2: CHAVE | B2: PERFIL | C2: TIPO DE FII | D2: %
A3: =$B$3&"-"&C3 -> Conservador-PAPEL | B3: Conservador | C3: PAPEL | D3: 0.3
A4: =$B$3&"-"&C4 -> Conservador-TIJOLO | B4: Conservador | C4: TIJOLO | D4: 0.5
A5: =$B$3&"-"&C5 -> Conservador-HÍBRIDOS | B5: Conservador | C5: HÍBRIDOS | D5: 0.1
A6: =$B$3&"-"&C6 -> Conservador-FOFs | B6: Conservador | C6: FOFs | D6: 0.1
A7: =$B$3&"-"&C7 -> Conservador-DESENVOLVIMENTO | B7: Conservador | C7: DESENVOLVIMENTO | D7: 0
A8: =$B$3&"-"&C8 -> Conservador-HOTELARIAS | B8: Conservador | C8: HOTELARIAS | D8: 0
A9: =$B$9&"-"&C9 -> Moderado-PAPEL | B9: Moderado | C9: PAPEL | D9: 0.32
A10: =$B$9&"-"&C10 -> Moderado-TIJOLO | B10: Moderado | C10: TIJOLO | D10: 0.35
A11: =$B$9&"-"&C11 -> Moderado-HÍBRIDOS | B11: Moderado | C11: HÍBRIDOS | D11: 0.08
A12: =$B$9&"-"&C12 -> Moderado-FOFs | B12: Moderado | C12: FOFs | D12: 0.05
A13: =$B$9&"-"&C13 -> Moderado-DESENVOLVIMENTO | B13: Moderado | C13: DESENVOLVIMENTO | D13: 0.1
A14: =$B$9&"-"&C14 -> Moderado-HOTELARIAS | B14: Moderado | C14: HOTELARIAS | D14: 0.1
A15: =$B$15&"-"&C15 -> Agressivo-PAPEL | B15: Agressivo | C15: PAPEL | D15: 0.5
A16: =$B$15&"-"&C16 -> Agressivo-TIJOLO | B16: Agressivo | C16: TIJOLO | D16: 0.1
A17: =$B$15&"-"&C17 -> Agressivo-HÍBRIDOS | B17: Agressivo | C17: HÍBRIDOS | D17: 0.05
A18: =$B$15&"-"&C18 -> Agressivo-FOFs | B18: Agressivo | C18: FOFs | D18: 0.05
A19: =$B$15&"-"&C19 -> Agressivo-DESENVOLVIMENTO | B19: Agressivo | C19: DESENVOLVIMENTO | D19: 0.2
A20: =$B$15&"-"&C20 -> Agressivo-HOTELARIAS | B20: Agressivo | C20: HOTELARIAS | D20: 0.1
